setup.cfg
setup.py
TelegramBotAPI/__init__.py
TelegramBotAPI.egg-info/PKG-INFO
TelegramBotAPI.egg-info/SOURCES.txt
TelegramBotAPI.egg-info/dependency_links.txt
TelegramBotAPI.egg-info/requires.txt
TelegramBotAPI.egg-info/top_level.txt
TelegramBotAPI/client/__init__.py
TelegramBotAPI/client/basic.py
TelegramBotAPI/client/twistedclient.py
TelegramBotAPI/types/__init__.py
TelegramBotAPI/types/compound.py
TelegramBotAPI/types/field.py
TelegramBotAPI/types/methods.py
TelegramBotAPI/types/primitive.py
TelegramBotAPI/types/type.py