Metadata-Version: 1.1
Name: TelegramBotAPI
Version: 0.2.1
Summary: Telegram Bot API
Home-page: https://github.com/sourcesimian/pyTelegramBotAPI
Author: Source Simian
Author-email: sourcesimian@users.noreply.github.com
License: MIT
Download-URL: https://github.com/sourcesimian/pyPlugin/tarball/v0.2.1
Platform: UNKNOWN
